{
  "url": "http://www.baomoi.com/Ho-bien-khu-tuong-dai-anh-hung-trong-rau-lam-be-chua-phan/121/13493381.epi",
  "time": "06/04/2014 09:44",
  "title": "Hô biến khu tượng đài anh hùng... trồng rau, làm bể chứa phân",
  "category": "Tin tức > Xã hội",
  "description": "(Kienthuc.net.vn) - Khu tượng đài “Tiếng bom Sấu giá” thuộc huyện Hoài Đức (Hà Nội) bị biến thành nơi trồng rau và thậm chí, người dân còn xây hẳn một bể chứa nước phân ngay dưới...",
  "content": "<tr> <td><span class='storyInlinePhoto'><img src='http://cms.kienthuc.net.vn/zoomh/500/uploaded/buimanhhung/2014_04_01/tuong%20dai%20sau%20gia/kienthuc_khu_dai_tuong_niem_bien_thanh_noi_trong_rau_xay_ho_phan%20(2)_zxxu.jpg' /></span> <div> Tượng đài Tiếng bom Sấu Giá là nơi ghi dấu sự gan dạ, dũng cảm, quyết tử cho tổ quốc quyết sinh của quân dân Hoài Đức trong cuộc kháng chiến chống thực dân Pháp năm 1947. </div> <span class='storyInlinePhoto'><img src='http://cms.kienthuc.net.vn/zoomh/500/uploaded/buimanhhung/2014_04_04/kienthuc_khu_dai_tuong_niem_bien_thanh_noi_trong_rau_xay_ho_phan%20(5)_txia_uqyc.jpg' /></span> <div> Tên của những vị tướng anh hùng dân tộc được ghi rõ trên tường trong khu tượng đài. </div> <span class='storyInlinePhoto'><img src='http://cms.kienthuc.net.vn/zoomh/500/uploaded/buimanhhung/2014_04_04/kienthuc_khu_dai_tuong_niem_bien_thanh_noi_trong_rau_xay_ho_phan%20(4)_dnwt_emmi.jpg' /></span> <div> Những chiến công lịch sử vang dội được in trên bảng di tích. </div> <span class='storyInlinePhoto'><img src='http://cms.kienthuc.net.vn/zoomh/500/uploaded/buimanhhung/2014_04_01/tuong%20dai%20sau%20gia/kienthuc_khu_dai_tuong_niem_bien_thanh_noi_trong_rau_xay_ho_phan%20(1)_mkma.jpg' /></span> <div> Tuy nhiên, tinh thần quyết cảm và những hình ảnh hào hùng của các chiến sĩ ngày ấy (nay được tôn thờ tại khu tượng đài Tiếng bom Sấu Giá) đang bị người dân nơi đây“bôi xấu” bằng những luống rau trồng ngang dọc ngay dưới chân tượng đài... </div> <span class='storyInlinePhoto'><img src='http://cms.kienthuc.net.vn/zoomh/500/uploaded/buimanhhung/2014_04_04/kienthuc_tuong_dai_anh_hung_rfsr.jpg' /></span> <div> ... và những đống rác thải chất đống vương vãi khắp nơi... </div> <span class='storyInlinePhoto'><img src='http://cms.kienthuc.net.vn/zoomh/500/uploaded/buimanhhung/2014_04_01/tuong%20dai%20sau%20gia/kienthuc_khu_dai_tuong_niem_bien_thanh_noi_trong_rau_xay_ho_phan%20(9)_kyky.jpg' /></span> <div> ... Thậm chí người dân còn xây hẳn một bể chứa nước phân bẩn ngay dưới chân của tượng đài. </div> <span class='storyInlinePhoto'><img src='http://cms.kienthuc.net.vn/zoomh/500/uploaded/buimanhhung/2014_04_01/tuong%20dai%20sau%20gia/kienthuc_khu_dai_tuong_niem_bien_thanh_noi_trong_rau_xay_ho_phan%20(8)_jwcj.jpg' /></span> <div> Cận cảnh bể nước phân đen ngòm, bốc mùi hôi thối. </div> <span class='storyInlinePhoto'><img src='http://cms.kienthuc.net.vn/zoomh/500/uploaded/buimanhhung/2014_04_01/tuong%20dai%20sau%20gia/kienthuc_khu_dai_tuong_niem_bien_thanh_noi_trong_rau_xay_ho_phan%20(7)_xnkp.jpg' /></span> <div> Những ống nước tự tạo để tưới rau chạy loằng ngoằng trong khu tượng đài. </div> <span class='storyInlinePhoto'><img src='http://cms.kienthuc.net.vn/zoomh/500/uploaded/buimanhhung/2014_04_01/tuong%20dai%20sau%20gia/kienthuc_khu_dai_tuong_niem_bien_thanh_noi_trong_rau_xay_ho_phan%20(10)_fixi.jpg' /></span> <div> Chiếc đồng hồ điện trong khu tượng đài có vỏ bao bọc tạm bợ, nhiều đoạn dây điện bị hở, bị đứt và được nối lại cực kỳ nguy hiểm. </div> <span class='storyInlinePhoto'><img src='http://cms.kienthuc.net.vn/zoomh/500/uploaded/buimanhhung/2014_04_01/tuong%20dai%20sau%20gia/kienthuc_khu_dai_tuong_niem_bien_thanh_noi_trong_rau_xay_ho_phan%20(11)_slpf.jpg' /></span> <div> Toàn khu tượng đài 'Tiếng bom Sấu Giá' chỉ thấy những luống rau, đống cỏ khô, rác thải... </div> <span class='storyInlinePhoto'><img src='http://cms.kienthuc.net.vn/zoomh/500/uploaded/buimanhhung/2014_04_01/tuong%20dai%20sau%20gia/kienthuc_khu_dai_tuong_niem_bien_thanh_noi_trong_rau_xay_ho_phan%20(3)_dfny.jpg' /></span><br /></td> </tr>",
  "key": [
    "tượng đài",
    "bể chứa",
    "bom",
    "nước phân",
    "trồng rau",
    "Hoài Đức",
    "anh hùng",
    "đống rác",
    "chất đống",
    "cỏ khô",
    "bể nước",
    "Hà Nội",
    "kháng chiến chống Pháp"
  ],
  "trends": [
    {
      "word": "ASEAN",
      "weight": "1"
    },
    {
      "word": "biên bản ghi nhớ",
      "weight": "5"
    },
    {
      "word": "biến đổi khí hậu",
      "weight": "2"
    },
    {
      "word": "biển Đông",
      "weight": "2"
    },
    {
      "word": "Bộ Tư Pháp",
      "weight": "4"
    },
    {
      "word": "Cửu Long",
      "weight": "6"
    },
    {
      "word": "Đà Nẵng",
      "weight": "3"
    },
    {
      "word": "Đền Hùng",
      "weight": "4"
    },
    {
      "word": "Đức",
      "weight": "6"
    },
    {
      "word": "Giỗ tổ Hùng Vương",
      "weight": "6"
    },
    {
      "word": "Hòa Bình",
      "weight": "4"
    },
    {
      "word": "Hoàng Sa",
      "weight": "3"
    },
    {
      "word": "Hoàng Trung Hải",
      "weight": "4"
    },
    {
      "word": "hội nghị cấp cao",
      "weight": "1"
    },
    {
      "word": "Lào",
      "weight": "3"
    },
    {
      "word": "Malaysia",
      "weight": "2"
    },
    {
      "word": "Mặt Trận Tổ Quốc Việt Nam",
      "weight": "6"
    },
    {
      "word": "Mê Kông",
      "weight": "2"
    },
    {
      "word": "MRC",
      "weight": "2"
    },
    {
      "word": "Mỹ",
      "weight": "3"
    },
    {
      "word": "Nguyễn Phú Trọng",
      "weight": "6"
    },
    {
      "word": "Nguyễn Tấn Dũng",
      "weight": "1"
    },
    {
      "word": "Nguyễn Xuân Phúc",
      "weight": "2"
    },
    {
      "word": "phát triển bền vững",
      "weight": "3"
    },
    {
      "word": "Phú Thọ",
      "weight": "5"
    },
    {
      "word": "Phùng Quang Thanh",
      "weight": "6"
    },
    {
      "word": "Sông Mekong",
      "weight": "1"
    },
    {
      "word": "Thanh Khê",
      "weight": "6"
    },
    {
      "word": "tố lốc",
      "weight": "4"
    },
    {
      "word": "Trung Quốc",
      "weight": "5"
    }
  ]
}
