{
  "Url": "http://www.baomoi.com/PTC-giai-trinh-chenh-lech-KQKD-sau-kiem-toan/127/13451414.epi",
  "Time": "01/04/2014 14:16",
  "Title": "PTC giải trình chênh lệch KQKD sau kiểm toán",
  "Category": "Tin tức > Kinh tế > Chứng khoán",
  "Description": "Lý do được đưa ra là các bút toán điều chỉnh liên quan đến chi phí quản lý doanh nghiệp.",
  "Content": "<tr> <td> <div itemprop='articleBody'> <p>Theo BCTC được kiểm toán năm 20113, CTCP Đầu tư và xây dựng Bưu điện ( PTC ) có lợi nhuận công ty mẹ đạt 552,70 triệu đồng, lợi nhuận hợp nhất đạt 1,42 tỉ đồng. Con số này có sự chênh lệch so với BCTC được PTC đưa ra trước đó. Cụ thể, trước kiểm toán, lợi nhuận công ty mẹ đạt 667,17 triệu đồng, lợi nhuận hợp nhất đạt 1,53 tỉ đồng.</p> <p>Việc lợi nhuận sụt giảm sau kiểm toán được giải thích là do các khoản chi phí quản lý doanh nghiệp được điều chỉnh tăng lên do hồ sơ được hoàn thiện sau thời điểm lập BCTC. Cụ thể là các khoản tiền điện thoại, xăng xe, chi phí hỗ trợ lương CBCNV để xử lý tồn tại ở các đơn vị, chi phí giao dịch, tiếp khách, đối ngoại, chi phí cải tạo, sửa chữa khu nhà ăn văn phòng. </p> <p>Hiện cổ phiếu PTC được giao dịch ở mức 6.800 đồng/cp, khối lượng giao dịch trung bình trong 10 phiên gần nhất chỉ đạt 87.073 cổ phiếu. Tổng giá trị vốn hóa thị trường của CLG hiện nay là 68 tỷ đồng.</p> </div><br /></td> </tr>",
  "Key": [
    "kiểm toán",
    "lợi nhuận",
    "công ty mẹ",
    "chi phí",
    "hợp nhất",
    "cổ phiếu",
    "vốn hóa",
    "giao dịch",
    "nhà ăn",
    "điều chỉnh",
    "khối lượng giao dịch"
  ],
  "Trends": [
    {
      "Word": "API",
      "Weight": "6"
    },
    {
      "Word": "báo cáo tài chính",
      "Weight": "4"
    },
    {
      "Word": "bất động sản",
      "Weight": "6"
    },
    {
      "Word": "cổ đông lớn",
      "Weight": "3"
    },
    {
      "Word": "cổ tức",
      "Weight": "1"
    },
    {
      "Word": "Công Lý",
      "Weight": "4"
    },
    {
      "Word": "công ty chứng khoán",
      "Weight": "3"
    },
    {
      "Word": "Công ty Cổ phần Đầu tư và Công nghiệp Tân Tạo",
      "Weight": "4"
    },
    {
      "Word": "Công ty cổ phần tập đoàn Đại Dương",
      "Weight": "5"
    },
    {
      "Word": "đại hội cổ đông",
      "Weight": "2"
    },
    {
      "Word": "dòng tiền",
      "Weight": "6"
    },
    {
      "Word": "HNX",
      "Weight": "1"
    },
    {
      "Word": "HNX-INDEX",
      "Weight": "3"
    },
    {
      "Word": "hội đồng quản trị",
      "Weight": "1"
    },
    {
      "Word": "HOSE",
      "Weight": "2"
    },
    {
      "Word": "kế hoạch kinh doanh",
      "Weight": "6"
    },
    {
      "Word": "kết quả kinh doanh",
      "Weight": "6"
    },
    {
      "Word": "khớp lệnh",
      "Weight": "3"
    },
    {
      "Word": "Ngân hàng TMCP Sài Gòn Hà Nội",
      "Weight": "3"
    },
    {
      "Word": "ngày giao dịch",
      "Weight": "6"
    },
    {
      "Word": "Nghị quyết Đại hội cổ đông",
      "Weight": "5"
    },
    {
      "Word": "phiên giao dịch",
      "Weight": "2"
    },
    {
      "Word": "sàn giao dịch chứng khoán",
      "Weight": "6"
    },
    {
      "Word": "SSI",
      "Weight": "3"
    },
    {
      "Word": "Standard \u0026 Poor's",
      "Weight": "4"
    },
    {
      "Word": "thị trường chứng khoán",
      "Weight": "5"
    },
    {
      "Word": "tính thanh khoản",
      "Weight": "2"
    },
    {
      "Word": "Tổng công ty Cổ phần Xây lắp Dầu khí Việt Nam",
      "Weight": "3"
    },
    {
      "Word": "VN-INDEX",
      "Weight": "1"
    },
    {
      "Word": "vốn hóa",
      "Weight": "5"
    }
  ]
}
