{
  "Url": "http://www.baomoi.com/Bao-Viet-co-tong-giam-doc-tam-thoi/45/13449995.epi",
  "Time": "01/04/2014 14:17",
  "Title": "Bảo Việt có tổng giám đốc tạm thời",
  "Category": "Tin tức > Kinh tế",
  "Description": "Ngày 31/3, Tập đoàn Bảo Việt đã có văn bản công bố thông tin về thay đổi nhân sự chủ chốt của tập đoàn.",
  "Content": "<tr> <td><p style='text-align: justify;'>Cụ thể, ông Trần Trọng Phúc sẽ thôi giữ chức Tổng giám đốc của Bảo Việt kể từ ngày 31/3/2014. Ông Trần Trọng Phúc cũng thôi không là thành viên HĐQT tập đoàn Bảo Việt.</p> <p style='text-align: justify;'>Tạm thời thay thế vị trí này là ông Dương Đức Chuyển – Thành viên Hội đồng quản trị kiêm Giám đốc Khối đầu tư của tập đoàn.</p> <p style='text-align: right;'><strong>T.Hà</strong></p><br /></td> </tr>",
  "Key": [
    "Bảo Việt",
    "tập đoàn",
    "hội đồng quản trị",
    "tổng giám đốc",
    "công bố thông tin",
    "thành viên",
    "chủ chốt",
    "nhân sự",
    "văn bản",
    "thay thế",
    "Đức"
  ],
  "Trends": [
    {
      "Word": "bất động sản",
      "Weight": "5"
    },
    {
      "Word": "Bloomberg",
      "Weight": "6"
    },
    {
      "Word": "Bộ Công Thương",
      "Weight": "2"
    },
    {
      "Word": "Bộ Tài Chính",
      "Weight": "3"
    },
    {
      "Word": "cổ tức",
      "Weight": "1"
    },
    {
      "Word": "công ty chứng khoán",
      "Weight": "4"
    },
    {
      "Word": "Cục Thuế",
      "Weight": "5"
    },
    {
      "Word": "đại hội cổ đông",
      "Weight": "2"
    },
    {
      "Word": "doanh nghiệp nhà nước",
      "Weight": "6"
    },
    {
      "Word": "DOJI",
      "Weight": "5"
    },
    {
      "Word": "gas",
      "Weight": "2"
    },
    {
      "Word": "GDP",
      "Weight": "6"
    },
    {
      "Word": "HNX",
      "Weight": "1"
    },
    {
      "Word": "HNX-INDEX",
      "Weight": "4"
    },
    {
      "Word": "hội đồng quản trị",
      "Weight": "1"
    },
    {
      "Word": "HOSE",
      "Weight": "2"
    },
    {
      "Word": "khớp lệnh",
      "Weight": "4"
    },
    {
      "Word": "lạm phát",
      "Weight": "6"
    },
    {
      "Word": "Ngân hàng Nhà nước Việt Nam",
      "Weight": "3"
    },
    {
      "Word": "Ngân hàng Phát triển Châu Á",
      "Weight": "4"
    },
    {
      "Word": "ngân hàng thương mại",
      "Weight": "6"
    },
    {
      "Word": "nợ xấu",
      "Weight": "3"
    },
    {
      "Word": "phiên giao dịch",
      "Weight": "2"
    },
    {
      "Word": "SJC",
      "Weight": "3"
    },
    {
      "Word": "SSI",
      "Weight": "4"
    },
    {
      "Word": "tính thanh khoản",
      "Weight": "3"
    },
    {
      "Word": "USD",
      "Weight": "1"
    },
    {
      "Word": "Vàng SJC",
      "Weight": "6"
    },
    {
      "Word": "VN-INDEX",
      "Weight": "1"
    },
    {
      "Word": "Vũ Huy Hoàng",
      "Weight": "6"
    }
  ]
}
