{
  "Url": "http://www.baomoi.com/Tha-ca-tren-song-Hau/45/13451722.epi",
  "Time": "01/04/2014 14:17",
  "Title": "Thả cá trên sông Hậu",
  "Category": "Tin tức > Kinh tế",
  "Description": "(TNO) Ngày 1.4, Chi cục Thủy sản tỉnh An Giang, UBND TP.Long Xuyên (An Giang) phối hợp các mạnh thường quân phóng sinh cá trên sông Hậu gồm 3.630 kg cá thịt và cá giống các loại, 291.050 con cá bản địa gồm cá hô, điêu hồng, cá tra, cá chép, cá trôi, mè vinh, rô phi...",
  "Content": "<tr> <td> <table width='100%'> <tbody> <tr> <td> </td> </tr> <tr> <td> </td> </tr> </tbody> </table> <div> <table align='center' width='100%'> <tbody> <tr> <td> <p><span class='storyInlinePhoto'><img src='http://www.thanhnien.com.vn/Pictures201404/Thanh_Luan/thaca.jpg' /></span> <span>Các ghe chở cá tiến ra sông Hậu</span></p> </td> </tr> </tbody> </table> <p>Tổng kinh phí đợt thả cá trên 230 triệu đồng.</p> <p>Trước đó ngày 14.2, tại huyện Phú Tân, An Giang, Trung tâm cá giống An Giang phối hợp 11 huyện, thị, thành ở An Giang và các mạnh thường quân trong và ngoài tỉnh thả 42 tấn cá thịt các loại, 25.000 con cá giống các loại với tổng kinh phí trên 1 tỉ đồng xuống sông Tiền nhằm tái tạo, bảo tồn nguồn lợi thủy sản và các loài cá quý hiếm bản địa.</p> <p><em>Tin, ảnh:</em> <strong>Thanh Dũng</strong></p> </div><br /></td> </tr> <tr> <td> </td> </tr> <tr> <td> </td> </tr> <tr> <td> <p><span class='storyInlinePhoto'><img src='http://www.thanhnien.com.vn/Pictures201404/Thanh_Luan/thaca.jpg' /></span> <span>Các ghe chở cá tiến ra sông Hậu</span></p> </td> </tr>",
  "Key": [
    "An Giang",
    "cá giống",
    "Sông Hậu",
    "thả cá",
    "cá thịt",
    "Mạnh Thường Quân",
    "bản địa",
    "thủy sản",
    "cá trôi",
    "Phú Tân",
    "cá hô",
    "ủy ban nhân dân thành phố",
    "Long Xuyên"
  ],
  "Trends": [
    {
      "Word": "bất động sản",
      "Weight": "5"
    },
    {
      "Word": "Bloomberg",
      "Weight": "6"
    },
    {
      "Word": "Bộ Công Thương",
      "Weight": "2"
    },
    {
      "Word": "Bộ Tài Chính",
      "Weight": "3"
    },
    {
      "Word": "cổ tức",
      "Weight": "1"
    },
    {
      "Word": "công ty chứng khoán",
      "Weight": "4"
    },
    {
      "Word": "Cục Thuế",
      "Weight": "5"
    },
    {
      "Word": "đại hội cổ đông",
      "Weight": "2"
    },
    {
      "Word": "doanh nghiệp nhà nước",
      "Weight": "6"
    },
    {
      "Word": "DOJI",
      "Weight": "5"
    },
    {
      "Word": "gas",
      "Weight": "2"
    },
    {
      "Word": "GDP",
      "Weight": "6"
    },
    {
      "Word": "HNX",
      "Weight": "1"
    },
    {
      "Word": "HNX-INDEX",
      "Weight": "4"
    },
    {
      "Word": "hội đồng quản trị",
      "Weight": "1"
    },
    {
      "Word": "HOSE",
      "Weight": "2"
    },
    {
      "Word": "khớp lệnh",
      "Weight": "4"
    },
    {
      "Word": "lạm phát",
      "Weight": "6"
    },
    {
      "Word": "Ngân hàng Nhà nước Việt Nam",
      "Weight": "3"
    },
    {
      "Word": "Ngân hàng Phát triển Châu Á",
      "Weight": "4"
    },
    {
      "Word": "ngân hàng thương mại",
      "Weight": "6"
    },
    {
      "Word": "nợ xấu",
      "Weight": "3"
    },
    {
      "Word": "phiên giao dịch",
      "Weight": "2"
    },
    {
      "Word": "SJC",
      "Weight": "3"
    },
    {
      "Word": "SSI",
      "Weight": "4"
    },
    {
      "Word": "tính thanh khoản",
      "Weight": "3"
    },
    {
      "Word": "USD",
      "Weight": "1"
    },
    {
      "Word": "Vàng SJC",
      "Weight": "6"
    },
    {
      "Word": "VN-INDEX",
      "Weight": "1"
    },
    {
      "Word": "Vũ Huy Hoàng",
      "Weight": "6"
    }
  ]
}
