{
  "Url": "http://www.baomoi.com/Vinh-danh-hoat-dong-sang-tao-cong-nghe/53/13449568.epi",
  "Time": "01/04/2014 14:19",
  "Title": "Vinh danh hoạt động sáng tạo công nghệ",
  "Category": "Tin tức > KH-CN",
  "Description": "(Chinhphu.vn) - Việc trao giải cho các giải pháp sáng tạo công nghệ lần thứ 12 là dịp khẳng định quyết tâm của người Việt Nam áp dụng tri thức vào thực tiễn cuộc sống.",
  "Content": "<tr> <td> <div> <table align='center' width='100%'> <tbody> <tr> <td><span class='storyInlinePhoto'><img src='http://baodientu.chinhphu.vn/Uploaded/nguyenvanhuan/2014_04_01/IMG_1865.JPG?maxwidth=460' /></span></td> </tr> <tr> <td>Chủ tịch Ủy ban Trung ương MTTQ Việt Nam trao giải thưởng cho các tác giả. Ảnh: VGP/Từ Lương</td> </tr> </tbody> </table> <p>Tối 31/3, Liên hiệp các Hội Khoa học và Kỹ thuật Việt Nam phối hợp với Bộ KHCN, Tổng Liên đoàn Lao động Việt Nam, Đoàn TNCS Hồ Chí Minh tổ chức Lễ trao giải thưởng Hội thi Sáng tạo kỹ thuật toàn quốc lần thứ 12 (2012-2013). </p> <p>Hội thi lần này đã thu hút được hàng nghìn giải pháp tham gia từ các hội thi cấp cơ sở, cấp tỉnh, thành phố và đã chọn 552 giải pháp xuất sắc nhất gửi Ban Tổ chức Hội thi toàn quốc xét trao giải.</p> <p>Ban Tổ chức đã quyết định trao giải thưởng cho 88 giải pháp, gồm: 5 giải Nhất; 11 giải Nhì; 24 giải Ba; 48 giải Khuyến khích thuộc 6 lĩnh vực, trong đó có các lĩnh vực về công nghệ thông tin, điện tử, viễn thông; cơ khí tự động hóa, xây dựng, giao thông vận tải; vật liệu, hóa chất, năng lượng; nông, lâm, ngư nghiệp, tài nguyên môi trường; y, dược; giáo dục, đào tạo...</p> <p>Nhân dịp này, Thủ tướng Chính phủ tặng Bằng khen cho 14 cá nhân là chủ nhiệm của 5 giải pháp đạt giải Nhất. Tổng Liên đoàn Lao động Việt Nam tặng 'Bằng Lao động Sáng tạo' cho các chủ nhiệm và đồng chủ nhiệm có các công trình đạt giải Nhất, Nhì, Ba. Các tác giả trẻ được Trung ương Đoàn TNCS Hồ Chí Minh tặng Bằng khen và Huy hiệu 'Tuổi trẻ sáng tạo'.</p> <p>Phát biểu chúc mừng các cá nhân đoạt giải thưởng, Chủ tịch Ủy ban Trung ương MTTQ Việt Nam Nguyễn Thiện Nhân nhấn mạnh các giải pháp công nghệ được tuyên dương hôm nay sẽ góp phần quan trọng vào nâng cao năng lực cạnh tranh của hàng hóa và Việt Nam trong nước cũng như trên thị trường quốc tế. <br /> <br /> Đồng chí Nguyễn Thiện Nhân mong muốn kết quả Hội thi sẽ góp phần tạo nên phong trào thi đua sáng tạo của 50 triệu công dân Việt Nam ở tuổi lao động trong cả nước.</p> <table align='center' width='100%'> <tbody> <tr> <td> <p>Trong số các giải thưởng, 3 giải pháp khoa học kỹ thuật được đánh giá xuất sắc nhất là: 'Sử dụng tàu định vị động lực học DP2 lắp đặt ống dẫn dầu trạm rót dầu không bến - FSO' của tác giả Đỗ Văn Phúc thuộc Xí nghiệp xây lắp, khảo sát và sửa chữa các công trình khai thác dầu khí-Vietsovpetro, góp phần tiết kiệm cho ngân sách 4,5 triệu USD mỗi lần lắp đặt ống dẫn dầu ở dàn khoan.</p> <p>- Giải pháp ứng dụng máy cắt kính an toàn bán tự động của kỹ sư Vũ Hoàng Sơn và cộng sự ở Hà Nội. Thiết bị góp phần giảm được 90% điện năng tiêu hao và giá thành chỉ bằng 1/20 thiết bị nhập khẩu.</p> <p>- Giải pháp công nghệ sản xuất bóng đá bằng da nhân tạo của tác giả Nguyễn Trọng Tuấn (Thanh Hóa) đã cạnh tranh rất hiệu quả với bóng đá sản xuất bằng da bò truyền thống với giá thành thấp hơn, có chất lượng cao hơn và sử dụng trong mọi thời tiết mà không ảnh hưởng tới thông số của trái bóng khi thi đấu. Sản phẩm được xuất khẩu tới 22 quốc gia phát triển.</p> <p>Giải tác giả nữ xuất sắc nhất được trao cho cô giáo Mai Thị Bích Nguyệt, Trường THCS An Vũ, Quỳnh Phụ, Thái Bình, Chủ nhiệm đề tài: 'Nghiên cứu, xây dựng phần mềm từ điển tiếng Việt, đồng âm, đồng nghĩa, trái nghĩa'.</p> </td> </tr> </tbody> </table> <div> <strong>Từ Lương </strong> </div> </div><br /></td> </tr> <tr> <td><span class='storyInlinePhoto'><img src='http://baodientu.chinhphu.vn/Uploaded/nguyenvanhuan/2014_04_01/IMG_1865.JPG?maxwidth=460' /></span></td> </tr> <tr> <td>Chủ tịch Ủy ban Trung ương MTTQ Việt Nam trao giải thưởng cho các tác giả. Ảnh: VGP/Từ Lương</td> </tr> <tr> <td> <p>Trong số các giải thưởng, 3 giải pháp khoa học kỹ thuật được đánh giá xuất sắc nhất là: 'Sử dụng tàu định vị động lực học DP2 lắp đặt ống dẫn dầu trạm rót dầu không bến - FSO' của tác giả Đỗ Văn Phúc thuộc Xí nghiệp xây lắp, khảo sát và sửa chữa các công trình khai thác dầu khí-Vietsovpetro, góp phần tiết kiệm cho ngân sách 4,5 triệu USD mỗi lần lắp đặt ống dẫn dầu ở dàn khoan.</p> <p>- Giải pháp ứng dụng máy cắt kính an toàn bán tự động của kỹ sư Vũ Hoàng Sơn và cộng sự ở Hà Nội. Thiết bị góp phần giảm được 90% điện năng tiêu hao và giá thành chỉ bằng 1/20 thiết bị nhập khẩu.</p> <p>- Giải pháp công nghệ sản xuất bóng đá bằng da nhân tạo của tác giả Nguyễn Trọng Tuấn (Thanh Hóa) đã cạnh tranh rất hiệu quả với bóng đá sản xuất bằng da bò truyền thống với giá thành thấp hơn, có chất lượng cao hơn và sử dụng trong mọi thời tiết mà không ảnh hưởng tới thông số của trái bóng khi thi đấu. Sản phẩm được xuất khẩu tới 22 quốc gia phát triển.</p> <p>Giải tác giả nữ xuất sắc nhất được trao cho cô giáo Mai Thị Bích Nguyệt, Trường THCS An Vũ, Quỳnh Phụ, Thái Bình, Chủ nhiệm đề tài: 'Nghiên cứu, xây dựng phần mềm từ điển tiếng Việt, đồng âm, đồng nghĩa, trái nghĩa'.</p> </td> </tr>",
  "Key": [
    "hội thi",
    "giải pháp",
    "sáng tạo",
    "trao giải",
    "ống dẫn dầu",
    "tác giả",
    "chủ nhiệm",
    "Tổng Liên Đoàn Lao Động Việt Nam",
    "Ủy ban Trung ương Mặt trận Tổ quốc Việt Nam",
    "góp phần",
    "bằng khen",
    "người Việt",
    "Liên hiệp các hội Khoa học và Kỹ thuật Việt Nam",
    "Bộ Khoa Học Và Công Nghệ",
    "Đoàn Thanh Niên Cộng Sản Hồ Chí Minh"
  ],
  "Trends": [
    {
      "Word": "Apple",
      "Weight": "1"
    },
    {
      "Word": "CEO",
      "Weight": "6"
    },
    {
      "Word": "chip",
      "Weight": "5"
    },
    {
      "Word": "độ phân giải",
      "Weight": "2"
    },
    {
      "Word": "Facebook",
      "Weight": "4"
    },
    {
      "Word": "Foxconn",
      "Weight": "6"
    },
    {
      "Word": "game online",
      "Weight": "5"
    },
    {
      "Word": "game thủ",
      "Weight": "2"
    },
    {
      "Word": "gameplay",
      "Weight": "4"
    },
    {
      "Word": "Google",
      "Weight": "2"
    },
    {
      "Word": "Google Android",
      "Weight": "1"
    },
    {
      "Word": "HTC",
      "Weight": "4"
    },
    {
      "Word": "HTC One",
      "Weight": "2"
    },
    {
      "Word": "iOS",
      "Weight": "3"
    },
    {
      "Word": "iPad",
      "Weight": "4"
    },
    {
      "Word": "iPhone",
      "Weight": "1"
    },
    {
      "Word": "lõi tứ",
      "Weight": "3"
    },
    {
      "Word": "Microsoft",
      "Weight": "4"
    },
    {
      "Word": "Ngày Cá tháng Tư",
      "Weight": "5"
    },
    {
      "Word": "Nokia",
      "Weight": "6"
    },
    {
      "Word": "online",
      "Weight": "6"
    },
    {
      "Word": "PIN",
      "Weight": "4"
    },
    {
      "Word": "RAM",
      "Weight": "6"
    },
    {
      "Word": "Samsung",
      "Weight": "2"
    },
    {
      "Word": "smartphone",
      "Weight": "1"
    },
    {
      "Word": "Sony",
      "Weight": "6"
    },
    {
      "Word": "Tablet PC",
      "Weight": "2"
    },
    {
      "Word": "Telco",
      "Weight": "4"
    },
    {
      "Word": "video",
      "Weight": "4"
    },
    {
      "Word": "Windows Phone",
      "Weight": "5"
    }
  ]
}
