{
  "Url": "http://www.baomoi.com/Tren-100000-ha-dat-nong-nghiep-tai-DBSCL-bi-xam-nhap-man/144/13450169.epi",
  "Time": "01/04/2014 14:18",
  "Title": "Trên 100.000 ha đất nông nghiệp tại ĐBSCL bị xâm nhập mặn",
  "Category": "Tin tức > Xã hội > Thời sự",
  "Description": "(VTV Online) - Tại khu vực ĐBSCL, tình trạng xâm nhập mặn năm nay được đánh giá là gay gắt hơn so với cùng kỳ năm ngoái.",
  "Content": "<tr> <td> <div> <p> </p> <div> Tại Hậu Giang, một số nơi độ mặn đo được đã lên đến 9‰. Mặn sẽ tiếp tục theo các triền sông xâm nhập sâu vào đất liền trong tháng 4/2014. Còn tại Cà Mau, có nơi độ mặn lên đến khoảng 30‰. Tình trạng thiếu nước ngọt trong sinh hoạt diễn ra ngày một gay gắt hơn. <br /> <br /> Trong khi đó, tình trạng khô hạn kèm theo nắng nóng làm hàng ngàn ha nuôi tôm sú, đất lúa của người dân thiệt hại nặng nề. Theo Bộ NN\u0026PTNT, hiện nay ĐBSCL có trên 100.000 ha đất sản xuất nông nghiệp bị xâm nhập mặn đe dọa, gây thiệt hại. <br /> </div> <p></p> <p> CBS </p> <br /> </div></td> </tr>",
  "Key": [
    "xâm nhập",
    "Đồng Bằng Sông Cửu Long",
    "triền sông",
    "khô hạn",
    "CBS",
    "nuôi tôm",
    "đất nông nghiệp",
    "thiếu nước",
    "Hậu Giang",
    "đất",
    "nắng nóng",
    "VTV",
    "online",
    "Cà Mau",
    "Bộ Nông Nghiệp Và Phát Triển Nông Thôn"
  ],
  "Trends": [
    {
      "Word": "ASIAD",
      "Weight": "1"
    },
    {
      "Word": "Bắc Bộ",
      "Weight": "5"
    },
    {
      "Word": "Bộ Công Thương",
      "Weight": "3"
    },
    {
      "Word": "Bộ Giao Thông Vận Tải",
      "Weight": "2"
    },
    {
      "Word": "Bộ Kế Hoạch Và Đầu Tư",
      "Weight": "6"
    },
    {
      "Word": "Bộ Văn hóa Thể Thao và Du lịch",
      "Weight": "2"
    },
    {
      "Word": "Cao Bằng",
      "Weight": "5"
    },
    {
      "Word": "chống tham nhũng",
      "Weight": "6"
    },
    {
      "Word": "Đà Nẵng",
      "Weight": "1"
    },
    {
      "Word": "độ kinh đông",
      "Weight": "5"
    },
    {
      "Word": "Hà Nội",
      "Weight": "3"
    },
    {
      "Word": "Huỳnh Phong Tranh",
      "Weight": "3"
    },
    {
      "Word": "Lạng Sơn",
      "Weight": "6"
    },
    {
      "Word": "Lào Cai",
      "Weight": "6"
    },
    {
      "Word": "liên đoàn lao động",
      "Weight": "6"
    },
    {
      "Word": "Miền Bắc",
      "Weight": "3"
    },
    {
      "Word": "Nguyễn Sinh Hùng",
      "Weight": "1"
    },
    {
      "Word": "Nhật Bản",
      "Weight": "5"
    },
    {
      "Word": "ODA",
      "Weight": "6"
    },
    {
      "Word": "Phạm Quang Nghị",
      "Weight": "5"
    },
    {
      "Word": "Quảng Nam",
      "Weight": "1"
    },
    {
      "Word": "Thăng Bình",
      "Weight": "3"
    },
    {
      "Word": "Thanh Tra Chính Phủ",
      "Weight": "2"
    },
    {
      "Word": "tố lốc",
      "Weight": "3"
    },
    {
      "Word": "Trung Bộ",
      "Weight": "5"
    },
    {
      "Word": "Trùng Khánh",
      "Weight": "6"
    },
    {
      "Word": "Ủy Ban Thường Vụ Quốc Hội",
      "Weight": "6"
    },
    {
      "Word": "VTV",
      "Weight": "6"
    },
    {
      "Word": "Vũ Đức Đam",
      "Weight": "3"
    },
    {
      "Word": "Vũ Huy Hoàng",
      "Weight": "2"
    }
  ]
}
