{
  "Url": "http://www.baomoi.com/Muon-som-co-con-dung-om-may-tinh/136/13450458.epi",
  "Time": "01/04/2014 14:19",
  "Title": "Muốn sớm có con, đừng 'ôm' máy tính",
  "Category": "Tin tức > KH-CN > Thiết bị - Phần cứng",
  "Description": "Sức nóng từ máy tính xách tay có thể làm giảm số lượng tinh trùng ở nam giới.",
  "Content": "<tr> <td> <div> <div> <p><span class='storyInlinePhoto'><img src='http://images.alobacsi.vn/Images/Uploaded/Share/2014/4/1/Muon-som-co-con-dung-om-may-tinh-1.jpg' /></span> <span class='storyInlinePhoto'><img src='http://images.alobacsi.vn/Images/Uploaded/Share/2014/4/1/Muon-som-co-con-dung-om-may-tinh-2.jpg' /></span> <span class='storyInlinePhoto'><img src='http://images.alobacsi.vn/Images/Uploaded/Share/2014/4/1/Muon-som-co-con-dung-om-may-tinh-3.jpg' /></span> <span class='storyInlinePhoto'><img src='http://images.alobacsi.vn/Images/Uploaded/Share/2014/4/1/Muon-som-co-con-dung-om-may-tinh-4.jpg' /></span></p> <p align='right'><span>AloBacsi.vn</span><br /><span>Theo Phong Lan - Khám phá</span></p> </div> </div><br /></td> </tr>",
  "Key": [
    "tinh trùng",
    "máy tính xách tay",
    "nam giới",
    "khám phá",
    "máy tính"
  ],
  "Trends": [
    {
      "Word": "Apple",
      "Weight": "1"
    },
    {
      "Word": "BlackBerry",
      "Weight": "6"
    },
    {
      "Word": "bộ nhớ trong",
      "Weight": "5"
    },
    {
      "Word": "chip",
      "Weight": "3"
    },
    {
      "Word": "độ phân giải",
      "Weight": "2"
    },
    {
      "Word": "Foxconn",
      "Weight": "3"
    },
    {
      "Word": "Full HD",
      "Weight": "6"
    },
    {
      "Word": "Google Android",
      "Weight": "1"
    },
    {
      "Word": "HTC",
      "Weight": "3"
    },
    {
      "Word": "HTC One",
      "Weight": "2"
    },
    {
      "Word": "iOS",
      "Weight": "4"
    },
    {
      "Word": "iPad",
      "Weight": "3"
    },
    {
      "Word": "iPhone",
      "Weight": "1"
    },
    {
      "Word": "iPhone 5",
      "Weight": "5"
    },
    {
      "Word": "LG",
      "Weight": "5"
    },
    {
      "Word": "lõi tứ",
      "Weight": "2"
    },
    {
      "Word": "Nokia",
      "Weight": "6"
    },
    {
      "Word": "PIN",
      "Weight": "3"
    },
    {
      "Word": "RAM",
      "Weight": "5"
    },
    {
      "Word": "Samsung",
      "Weight": "1"
    },
    {
      "Word": "Samsung Galaxy Note",
      "Weight": "6"
    },
    {
      "Word": "SIM",
      "Weight": "5"
    },
    {
      "Word": "smartphone",
      "Weight": "1"
    },
    {
      "Word": "Sony",
      "Weight": "6"
    },
    {
      "Word": "Tablet PC",
      "Weight": "2"
    },
    {
      "Word": "Telco",
      "Weight": "4"
    },
    {
      "Word": "video",
      "Weight": "6"
    },
    {
      "Word": "Weibo",
      "Weight": "5"
    },
    {
      "Word": "wifi",
      "Weight": "6"
    },
    {
      "Word": "Windows Phone",
      "Weight": "5"
    }
  ]
}
