{
  "url": "http://www.baomoi.com/HLV-Mazzarri-muon-dien-voi-phong-thay-do-cua-Inter/87/13494381.epi",
  "time": "06/04/2014 09:44",
  "title": "HLV Mazzarri muốn 'điên' với phòng thay đồ của Inter",
  "category": "Tin tức > Thể thao > Bóng đá",
  "description": "(TinTheThao.com.vn) - HLV thừa nhận ông vô cùng thất vọng khi .",
  "content": "<tr> <td> <div align='justify'> <div align='justify'> <table align='center' summary='' width='100%'> <tbody> <tr> <td> <span class='storyInlinePhoto'><img src='http://img.tinthethao.com.vn/uploads/news/PostImg/2014/04/06/46/95340b914c4bd3.jpg' /></span></td> </tr> </tbody> </table> Đây đã là trận thứ 4 liên tiếp mà Inter không thắng, và đó cũng là trận thứ 3 liên tiếp mà đội bóng này buộc phải chia điểm với đối thủ, và điều này cũng đang khiến cho Nerazzurri có nguy cơ đánh mất vị trí 5 (tham dự Europa League) của mình trong mùa giải năm sau. <br /> <br /> Phát biểu sau trận hòa trước Bologna, HLV Mazzarri đã tỏ ra khá bức xúc khi cho biết: <i> 'Thật khó tin, chúng tôi đã bỏ lỡ quá nhiều cơ hội, thậm chí là cả một quả penalty (Milito sút hỏng).'<br /> <br /> 'Tuy nhiên tôi sẽ không nói rằng chúng tôi đã kém may mắn trong trận đấu này. Nhưng đó cũng có thể được xem là một tai nạn.'<br /> <br /> 'Phải thừa nhận rằng tôi đang có phần hối hận khi quá mềm mỏng với các cầu thủ trong khoảng thời gian nghỉ giữ hai hiệp, tôi đáng ra phải đập tan cả phòng thay đồ vào thời điểm ấy để kích thích tình thần thi đấu của các cầu thủ.'</i> </div> </div><br /></td> </tr> <tr> <td> <span class='storyInlinePhoto'><img src='http://img.tinthethao.com.vn/uploads/news/PostImg/2014/04/06/46/95340b914c4bd3.jpg' /></span></td> </tr>",
  "key": [
    "phòng thay đồ",
    "Inter Milan",
    "huấn luyện viên",
    "Europa League",
    "Nerazzurri",
    "đập tan",
    "Bologna",
    "thừa nhận",
    "cầu thủ",
    "quả phạt đền",
    "hối hận"
  ],
  "trends": [
    {
      "word": "Adnan Januzaj",
      "weight": "4"
    },
    {
      "word": "Arsenal",
      "weight": "3"
    },
    {
      "word": "Arsene Wenger",
      "weight": "6"
    },
    {
      "word": "Barcelona",
      "weight": "1"
    },
    {
      "word": "Bayern Munich",
      "weight": "5"
    },
    {
      "word": "Champions League",
      "weight": "3"
    },
    {
      "word": "Chelsea",
      "weight": "1"
    },
    {
      "word": "David Moyes",
      "weight": "2"
    },
    {
      "word": "Edin Džeko",
      "weight": "6"
    },
    {
      "word": "Everton",
      "weight": "6"
    },
    {
      "word": "Fernando Torres",
      "weight": "4"
    },
    {
      "word": "Giải ngoại hạng Anh",
      "weight": "2"
    },
    {
      "word": "Hoàng Anh Gia Lai",
      "weight": "5"
    },
    {
      "word": "Javier Hernández",
      "weight": "5"
    },
    {
      "word": "José Mourinho",
      "weight": "2"
    },
    {
      "word": "Juan Mata",
      "weight": "2"
    },
    {
      "word": "Lionel Messi",
      "weight": "4"
    },
    {
      "word": "Liverpool",
      "weight": "3"
    },
    {
      "word": "Manchester City",
      "weight": "1"
    },
    {
      "word": "Manchester United",
      "weight": "1"
    },
    {
      "word": "Manuel Pellegrini",
      "weight": "6"
    },
    {
      "word": "Newcastle",
      "weight": "2"
    },
    {
      "word": "PSG",
      "weight": "3"
    },
    {
      "word": "Quỷ Đỏ",
      "weight": "5"
    },
    {
      "word": "Real Betis",
      "weight": "5"
    },
    {
      "word": "Real Madrid",
      "weight": "1"
    },
    {
      "word": "Real Sociedad",
      "weight": "4"
    },
    {
      "word": "Samir Nasri",
      "weight": "6"
    },
    {
      "word": "Shinji Kagawa",
      "weight": "4"
    },
    {
      "word": "Southampton",
      "weight": "3"
    }
  ]
}
