{
  "Url": "http://www.baomoi.com/Trung-Quoc-trieu-Dai-su-Philippines-de-phan-doi-vu-kien/119/13452043.epi",
  "Time": "01/04/2014 14:15",
  "Title": "Trung Quốc triệu Đại sứ Philippines để phản đối vụ kiện",
  "Category": "Tin tức > Thế giới",
  "Description": "VOV.VN - Trung Quốc cho rằng, vụ kiện này không giúp ích cho việc giải quyết tranh chấp giữa 2 nước ở Biển Đông.",
  "Content": "<tr> <td> <div> <p>Ngày 31/3, Bộ Ngoại giao Trung Quốc đã triệu Đại sứ Philippines tại Bắc Kinh để bày tỏ thái độ không hài lòng trước việc Manila nộp bằng chứng lên tòa án quốc tế nhằm phản đối các yêu sách về lãnh thổ trên biển của Bắc Kinh. </p> <table align='center' width='100%'> <tbody> <tr> <td><span class='storyInlinePhoto'><img src='http://vov.vn/Uploaded/trancuong/2014_04_01/thu_truong-TQ.jpg' /></span> </td> </tr> <tr> <td>Thứ trưởng Ngoại giao Trung Quốc Lưu Chấn Dân (Ảnh: Tân Hoa xã)<br /> </td> </tr> </tbody> </table> <p>Theo <em>Reuters</em>, Thứ trưởng Ngoại giao Trung Quốc Lưu Chấn Dân nói với Đại sứ Philippines rằng, Bắc Kinh 'hoàn toàn không đồng tình và cực lực phản đối' vụ việc mà Manila vừa đệ trình lên tòa án quốc tế ở The Hague (Hà Lan), đồng thời tái khẳng định sẽ không chấp nhận và không tham gia vụ kiện.</p> <p>Ông Lưu nói: 'Việc Philippines theo đuổi sự phân sử quốc tế không có ích gì đối với việc giải quyết tranh chấp giữa hai nước ở Biển Đông. Bước đi đó cũng không làm lay chuyển quyết tâm của Trung Quốc trong việc bảo vệ chủ quyền và toàn vẹn lãnh thổ”. </p> <p>Theo ông Lưu, cách duy nhất để giải quyết vấn đề là thông qua đàm phán song phương. Đây là lập trường mà Bắc Kinh khăng khăng theo đuổi trong các tranh chấp ở Biển Đông. Thông qua cách này, Trung Quốc hy vọng có thể để dễ bề gây áp lực lên các nước khác và giành nhiều lợi thế hơn so với việc tiến hành đàm phán đa phương.</p> <p>Trước đó, hôm 30/3, Manila đã đệ trình 4.000 trang phân tích và bằng chứng văn bản lên Tòa án quốc tế ở The Hague. Theo đó, Philippines đề nghị tòa án tuyên bố rằng, yêu sách của Trung Quốc đòi chủ quyền phi lý ở Biển Đông là bất hợp pháp.</p> <p>Cũng theo <em>Reuters</em>, phát biểu với các phóng viên ngày 31/3, Tổng thống Philippines, ông Benigno Aquino cho biết Philippines không có định đối đầu với Trung Quốc mà chỉ nhằm bảo vệ chủ quyền quốc gia của nước này một cách hòa bình./.</p> <p> Hùng Cường/VOV online </p> </div><br /></td> </tr> <tr> <td><span class='storyInlinePhoto'><img src='http://vov.vn/Uploaded/trancuong/2014_04_01/thu_truong-TQ.jpg' /></span> </td> </tr> <tr> <td>Thứ trưởng Ngoại giao Trung Quốc Lưu Chấn Dân (Ảnh: Tân Hoa xã)<br /> </td> </tr>",
  "Key": [
    "Philippines",
    "tòa án quốc tế",
    "biển Đông",
    "Trung Quốc",
    "Manila",
    "chủ quyền",
    "Bắc Kinh",
    "vụ kiện",
    "Den Haag",
    "đại sứ",
    "yêu sách",
    "Bộ Ngoại Giao",
    "Tân Hoa Xã",
    "Reuters",
    "Hà Lan"
  ],
  "Trends": [
    {
      "Word": "Ấn Độ Dương",
      "Weight": "4"
    },
    {
      "Word": "Australia",
      "Weight": "5"
    },
    {
      "Word": "biển Đông",
      "Weight": "3"
    },
    {
      "Word": "Bình Nhưỡng",
      "Weight": "2"
    },
    {
      "Word": "Bộ Ngoại Giao",
      "Weight": "6"
    },
    {
      "Word": "Bộ Quốc Phòng",
      "Weight": "5"
    },
    {
      "Word": "Crimea",
      "Weight": "1"
    },
    {
      "Word": "đặc khu kinh tế",
      "Weight": "5"
    },
    {
      "Word": "Dmitry Medvedev",
      "Weight": "2"
    },
    {
      "Word": "François Hollande",
      "Weight": "6"
    },
    {
      "Word": "Hàn Quốc",
      "Weight": "1"
    },
    {
      "Word": "John Kerry",
      "Weight": "3"
    },
    {
      "Word": "Kiev",
      "Weight": "5"
    },
    {
      "Word": "Liên Hợp Quốc",
      "Weight": "5"
    },
    {
      "Word": "Liên minh châu Âu",
      "Weight": "4"
    },
    {
      "Word": "Malaysia",
      "Weight": "2"
    },
    {
      "Word": "Malaysia Airlines",
      "Weight": "6"
    },
    {
      "Word": "Moscow",
      "Weight": "4"
    },
    {
      "Word": "Mỹ",
      "Weight": "3"
    },
    {
      "Word": "NATO",
      "Weight": "6"
    },
    {
      "Word": "Nga",
      "Weight": "1"
    },
    {
      "Word": "ngoại trưởng Mỹ",
      "Weight": "5"
    },
    {
      "Word": "Ngoại trưởng Nga",
      "Weight": "6"
    },
    {
      "Word": "Nhật Bản",
      "Weight": "4"
    },
    {
      "Word": "Philippines",
      "Weight": "3"
    },
    {
      "Word": "thủ tướng Nga",
      "Weight": "2"
    },
    {
      "Word": "Triều Tiên",
      "Weight": "1"
    },
    {
      "Word": "Trung Quốc",
      "Weight": "2"
    },
    {
      "Word": "Ukraina",
      "Weight": "1"
    },
    {
      "Word": "Vladimir Putin",
      "Weight": "3"
    }
  ]
}
