{
  "Url": "http://www.baomoi.com/Lufthansa-huy-3800-chuyen-bay-trong-tuan-nay/119/13450895.epi",
  "Time": "01/04/2014 14:15",
  "Title": "Lufthansa hủy 3.800 chuyến bay trong tuần này",
  "Category": "Tin tức > Thế giới",
  "Description": "(TBKTSG Online) – Hãng hàng không Lufthansa (Đức) ngày 31-3 thông báo sẽ hủy 3.800 chuyến bay trong tuần này do các cuộc đình công của phi công.",
  "Content": "<tr> <td><span><p></p><p>Trúc Như</p> <table align='left' width='100%'> <tbody> <tr> <td align='center'> <span class='storyInlinePhoto'><img src='http://www.thesaigontimes.vn/Uploads/Articles/112720/841c6__73929340_lusv1tz7.jpg' /></span></td> </tr> <tr> <td> Lufthansa sẽ hủy 3.800 chuyến bay trong tuần này. Ảnh: Reuters</td> </tr> </tbody> </table> <p align='left'> </p> <p> Dự kiến, hơn 425.000 hành khách của hãng sẽ bị trì hoãn chuyến bay từ ngày 2-4 đến 4-4.</p> <p> Bên cạnh đó, dịch vụ vận chuyển hàng hóa của Lufthansa cũng bị ảnh hưởng.</p> <p> Các hành khách bị hủy chuyến bay sẽ được thông báo qua tin nhắn hoặc email về những thay đổi của chuyến bay. Hãng Lufthansa đã có một số biện pháp cải thiện tình hình như cung cấp cho khách hàng cơ hội để mở rộng ngày bay miễn vé...</p> <p> Cuộc đình công của các phi công lần này nhằm yêu cầu hãng tăng lương và cải thiện điều kiện lao động. Lufthansa cho biết đây sẽ là một trong những cuộc đình công lớn nhất trong lịch sử của hãng.</p> <p> Tuần trước, Lufthansa cũng đã hủy hơn 600 chuyến bay do nhân viên sân bay đình công.</p> </span><br /></td> </tr> <tr> <td align='center'> <span class='storyInlinePhoto'><img src='http://www.thesaigontimes.vn/Uploads/Articles/112720/841c6__73929340_lusv1tz7.jpg' /></span></td> </tr> <tr> <td> Lufthansa sẽ hủy 3.800 chuyến bay trong tuần này. Ảnh: Reuters</td> </tr>",
  "Key": [
    "Lufthansa",
    "chuyến bay",
    "hủy",
    "đình công",
    "phi công",
    "hành khách",
    "cải thiện",
    "tăng lương",
    "trì hoãn",
    "hãng hàng không",
    "thông báo",
    "Đức",
    "Reuters",
    "Email"
  ],
  "Trends": [
    {
      "Word": "Ấn Độ Dương",
      "Weight": "4"
    },
    {
      "Word": "Australia",
      "Weight": "5"
    },
    {
      "Word": "biển Đông",
      "Weight": "3"
    },
    {
      "Word": "Bình Nhưỡng",
      "Weight": "2"
    },
    {
      "Word": "Bộ Ngoại Giao",
      "Weight": "6"
    },
    {
      "Word": "Bộ Quốc Phòng",
      "Weight": "5"
    },
    {
      "Word": "Crimea",
      "Weight": "1"
    },
    {
      "Word": "đặc khu kinh tế",
      "Weight": "5"
    },
    {
      "Word": "Dmitry Medvedev",
      "Weight": "2"
    },
    {
      "Word": "François Hollande",
      "Weight": "6"
    },
    {
      "Word": "Hàn Quốc",
      "Weight": "1"
    },
    {
      "Word": "John Kerry",
      "Weight": "3"
    },
    {
      "Word": "Kiev",
      "Weight": "5"
    },
    {
      "Word": "Liên Hợp Quốc",
      "Weight": "5"
    },
    {
      "Word": "Liên minh châu Âu",
      "Weight": "4"
    },
    {
      "Word": "Malaysia",
      "Weight": "2"
    },
    {
      "Word": "Malaysia Airlines",
      "Weight": "6"
    },
    {
      "Word": "Moscow",
      "Weight": "4"
    },
    {
      "Word": "Mỹ",
      "Weight": "3"
    },
    {
      "Word": "NATO",
      "Weight": "6"
    },
    {
      "Word": "Nga",
      "Weight": "1"
    },
    {
      "Word": "ngoại trưởng Mỹ",
      "Weight": "5"
    },
    {
      "Word": "Ngoại trưởng Nga",
      "Weight": "6"
    },
    {
      "Word": "Nhật Bản",
      "Weight": "4"
    },
    {
      "Word": "Philippines",
      "Weight": "3"
    },
    {
      "Word": "thủ tướng Nga",
      "Weight": "2"
    },
    {
      "Word": "Triều Tiên",
      "Weight": "1"
    },
    {
      "Word": "Trung Quốc",
      "Weight": "2"
    },
    {
      "Word": "Ukraina",
      "Weight": "1"
    },
    {
      "Word": "Vladimir Putin",
      "Weight": "3"
    }
  ]
}
