{
  "url": "http://www.baomoi.com/Khoi-to-giam-doc-cong-ty-lam-gia-tai-lieu/58/13494248.epi",
  "time": "06/04/2014 09:44",
  "title": "Khởi tố giám đốc công ty làm giả tài liệu",
  "category": "Tin tức > Pháp luật ",
  "description": "TT - Ngày 5-4, thông tin từ Cơ quan an ninh điều tra Công an tỉnh Cà Mau cho biết đã ra quyết định khởi tố bị can cho tại ngoại bà Nguyễn Cẩm Nhung (giám đốc Công ty TNHH Hưng Điền, trụ sở tại huyện Trần Văn Thời) về hành vi “làm giả con dấu, tài liệu của cơ quan, tổ chức”.",
  "content": "<tr> <td><p>Quyết định đã được viện kiểm sát cùng cấp phê duyệt và tống đạt đến bà Nhung. Bà Nhung là vợ ông Nguyễn Quốc Định, nguyên giám đốc Sở Xây dựng tỉnh Cà Mau, hiện bị điều về Ban tổ chức Tỉnh ủy.</p> <p>Trước đó tháng 11-2013, Thanh tra tỉnh Cà Mau đã công bố kết luận thanh tra việc chấp hành chính sách, pháp luật của Nhà nước tại Sở Xây dựng khi ông Định còn làm giám đốc. Theo đó, Công ty TNHH Hưng Điền đã làm giả tài liệu của Sở Xây dựng và Ban quản lý dự án khu đô thị Đông Bắc đi chứng thực. Sau đó sử dụng tài liệu này nộp cho một chi nhánh ngân hàng trên địa bàn tỉnh Cà Mau để giải chấp trước hạn nhằm ký quỹ chứng thư bảo lãnh dự thầu.</p> <p>Bằng cách sử dụng các chứng từ bảo lãnh giả để tham gia dự thầu, Công ty TNHH Hưng Điền đã qua mặt cơ quan chức năng trúng thầu trái quy định tám gói thầu tại Sở Xây dựng tỉnh Cà Mau với tổng trị giá 30 tỉ đồng.</p> <p>TẤN THÁI</p><br /></td> </tr>",
  "key": [
    "Sở Xây dựng",
    "Cà Mau",
    "làm giả",
    "tài liệu",
    "giám đốc",
    "bảo lãnh dự thầu",
    "giải chấp",
    "thanh tra",
    "khởi tố",
    "Trần Văn Thời",
    "chứng thư",
    "Cơ quan an ninh điều tra",
    "Viện Kiểm Sát",
    "tống đạt",
    "ban quản lý dự án"
  ],
  "trends": [
    {
      "word": "bắt giữ",
      "weight": "5"
    },
    {
      "word": "bắt quả tang",
      "weight": "3"
    },
    {
      "word": "Bệnh viện Nhi đồng 1",
      "weight": "3"
    },
    {
      "word": "chém",
      "weight": "5"
    },
    {
      "word": "Cơ quan cảnh sát điều tra",
      "weight": "4"
    },
    {
      "word": "cướp",
      "weight": "1"
    },
    {
      "word": "Đà Nẵng",
      "weight": "5"
    },
    {
      "word": "giết người",
      "weight": "4"
    },
    {
      "word": "He-rô-in",
      "weight": "3"
    },
    {
      "word": "hiếp dâm",
      "weight": "2"
    },
    {
      "word": "kháng cáo",
      "weight": "6"
    },
    {
      "word": "khiêu dâm",
      "weight": "6"
    },
    {
      "word": "khởi tố",
      "weight": "2"
    },
    {
      "word": "khống chế",
      "weight": "6"
    },
    {
      "word": "Lê Duẩn",
      "weight": "4"
    },
    {
      "word": "Nghệ An",
      "weight": "3"
    },
    {
      "word": "Nghi Lộc",
      "weight": "4"
    },
    {
      "word": "Phan Đăng Lưu",
      "weight": "6"
    },
    {
      "word": "phòng cháy chữa cháy",
      "weight": "1"
    },
    {
      "word": "Quận 8",
      "weight": "1"
    },
    {
      "word": "Quảng Nam",
      "weight": "6"
    },
    {
      "word": "Sở Giao thông Vận tải",
      "weight": "6"
    },
    {
      "word": "sơ thẩm",
      "weight": "4"
    },
    {
      "word": "tháng tù giam",
      "weight": "6"
    },
    {
      "word": "tòa án nhân dân",
      "weight": "1"
    },
    {
      "word": "trái phép",
      "weight": "3"
    },
    {
      "word": "trinh sát",
      "weight": "3"
    },
    {
      "word": "trộm cắp",
      "weight": "1"
    },
    {
      "word": "video clip",
      "weight": "2"
    },
    {
      "word": "Vinh",
      "weight": "3"
    }
  ]
}
